pyravin/__init__.py
pyravin/google/__init__.py
pyravin/google/calendar.py
pyravin/google/constant.py
pyravin/google/exception.py
pyravin/google/oauth.py
pyravin/google/utils.py
pyravin/zoom/__init__.py
pyravin-0.0.6.dist-info/LICENSE
pyravin-0.0.6.dist-info/METADATA
pyravin-0.0.6.dist-info/WHEEL
pyravin-0.0.6.dist-info/top_level.txt
pyravin-0.0.6.dist-info/RECORD
